README.md
setup.py
atmeexpy/__init__.py
atmeexpy/auth.py
atmeexpy/client.py
atmeexpy/const.py
atmeexpy/device.py
atmeexpy/models.py
atmeexpy.egg-info/PKG-INFO
atmeexpy.egg-info/SOURCES.txt
atmeexpy.egg-info/dependency_links.txt
atmeexpy.egg-info/requires.txt
atmeexpy.egg-info/top_level.txt