Metadata-Version: 2.1
Name: atmeexpy
Version: 0.1.2
Summary: Atmeex cloud api
Home-page: https://github.com/anpavlov/atmeexpy
Download-URL: 
Author: Andrey Pavlov
Author-email: dir94@mail.ru
